damage_layers/__init__.py
damage_layers/layers.py
damage_layers-0.2.dist-info/METADATA
damage_layers-0.2.dist-info/WHEEL
damage_layers-0.2.dist-info/top_level.txt
damage_layers-0.2.dist-info/RECORD
